cflw/__init__.py
cflw/__main__.py
cflw/cflw.py
cflw/cflw_v0_12_1.py
cflw/cflw_v0_9_1.py
cflw-0.12.1.dist-info/LICENSE
cflw-0.12.1.dist-info/METADATA
cflw-0.12.1.dist-info/WHEEL
cflw-0.12.1.dist-info/top_level.txt
cflw-0.12.1.dist-info/RECORD
