Metadata-Version: 2.1
Name: cflw
Version: 0.12.1
Summary: Control flow framework for running of state graphs
Author-email: "Th. P." <none@example.org>
Project-URL: Homepage, https://codeberg.org/thpit/cflw/
Project-URL: Bug Tracker, https://codeberg.org/thpit/cflw/
Classifier: Development Status :: 4 - Beta
Classifier: Programming Language :: Python :: 3
Classifier: Operating System :: OS Independent
Classifier: Intended Audience :: Financial and Insurance Industry
Classifier: Intended Audience :: Healthcare Industry
Classifier: Intended Audience :: Information Technology
Classifier: Intended Audience :: Science/Research
Classifier: Topic :: Utilities
Requires-Python: >=3.7
License-File: LICENSE
